django_ga4_serverside/__init__.py
django_ga4_serverside/apps.py
django_ga4_serverside/middleware.py
django_ga4_serverside/utils.py
django_ga4_serverside/signals/__init__.py
django_ga4_serverside/signals/handlers.py
django_ga4_serverside-0.0.2.dist-info/AUTHORS
django_ga4_serverside-0.0.2.dist-info/LICENSE
django_ga4_serverside-0.0.2.dist-info/METADATA
django_ga4_serverside-0.0.2.dist-info/WHEEL
django_ga4_serverside-0.0.2.dist-info/top_level.txt
django_ga4_serverside-0.0.2.dist-info/RECORD
