Metadata-Version: 2.1
Name: django-ga4-serverside
Version: 0.0.2
Summary: Server side GA4 tracking
Author-email: Miroslav Bendík <miroslav.bendik@gmail.com>
License: MIT
Project-URL: homepage, https://github.com/mireq/django-ga4-serverside
Project-URL: documentation, https://github.com/mireq/django-ga4-serverside
Project-URL: repository, https://github.com/mireq/django-ga4-serverside
Project-URL: changelog, https://github.com/mireq/django-ga4-serverside/blob/master/CHANGELOG.md
Keywords: django
Classifier: Environment :: Web Environment
Classifier: Framework :: Django
Classifier: Intended Audience :: Developers
Classifier: License :: OSI Approved :: BSD License
Classifier: Operating System :: OS Independent
Classifier: Programming Language :: Python
Classifier: Programming Language :: Python :: 3
Classifier: Topic :: Internet :: WWW/HTTP
Classifier: Topic :: Internet :: WWW/HTTP :: Dynamic Content
Requires-Python: >=3.7
License-File: LICENSE
License-File: AUTHORS
Requires-Dist: django
Requires-Dist: crawlerdetect
Requires-Dist: contextvars ; python_version < "3.7"
Requires-Dist: dataclasses ; python_version < "3.7"
Provides-Extra: dev
Requires-Dist: tox ; extra == 'dev'
Requires-Dist: pylint ; extra == 'dev'
Requires-Dist: pre-commit ; extra == 'dev'
Requires-Dist: bump2version ; extra == 'dev'
Requires-Dist: commitizen ; extra == 'dev'
